{
  "output": [
    {
      "id": 0,
      "protocol": "abd",
      "m": 5,
      "selected_dcs": [
        0,
        2,
        5,
        7,
        8
      ],
      "get_cost": 4.649400000000001e-05,
      "put_cost": 5.165999999999999e-06,
      "storage_cost": 3.123287671232877e-07,
      "vm_cost": 0.411576,
      "total_cost": 0.41162797232876713,
      "get_latency": 656.2,
      "put_latency": 656.2,
      "iq1": [
        5,
        7,
        8
      ],
      "iq2": [
        5,
        7,
        8
      ]
    },
    {
      "id": 1,
      "protocol": "replication",
      "m": 5,
      "k": 1,
      "selected_dcs": [
        0,
        2,
        5,
        7,
        8
      ],
      "get_cost": 0.027108108000000002,
      "put_cost": 0.002167326,
      "storage_cost": 0.00031264109589041096,
      "vm_cost": 0.411576,
      "total_cost": 0.4411640750958904,
      "get_latency": 656.2,
      "put_latency": 984.3000000000001,
      "iq1": [
        5,
        7,
        8
      ],
      "iq2": [
        5,
        7,
        8
      ],
      "iq3": [
        5,
        7,
        8
      ],
      "iq4": [
        5,
        7,
        8
      ]
    },
    {
      "id": 2,
      "protocol": "replication",
      "m": 5,
      "k": 1,
      "selected_dcs": [
        0,
        2,
        5,
        7,
        8
      ],
      "get_cost": 0.05416210800000001,
      "put_cost": 0.004327326,
      "storage_cost": 0.0006249698630136985,
      "vm_cost": 0.411576,
      "total_cost": 0.4706904038630137,
      "get_latency": 656.2,
      "put_latency": 984.3000000000001,
      "iq1": [
        5,
        7,
        8
      ],
      "iq2": [
        5,
        7,
        8
      ],
      "iq3": [
        5,
        7,
        8
      ],
      "iq4": [
        5,
        7,
        8
      ]
    },
    {
      "id": 3,
      "protocol": "replication",
      "m": 5,
      "k": 1,
      "selected_dcs": [
        0,
        2,
        5,
        7,
        8
      ],
      "get_cost": 0.08121610800000001,
      "put_cost": 0.006487326,
      "storage_cost": 0.0009372986301369862,
      "vm_cost": 0.411576,
      "total_cost": 0.500216732630137,
      "get_latency": 656.2,
      "put_latency": 984.3000000000001,
      "iq1": [
        5,
        7,
        8
      ],
      "iq2": [
        5,
        7,
        8
      ],
      "iq3": [
        5,
        7,
        8
      ],
      "iq4": [
        5,
        7,
        8
      ]
    },
    {
      "id": 4,
      "protocol": "replication",
      "m": 5,
      "k": 1,
      "selected_dcs": [
        0,
        2,
        5,
        7,
        8
      ],
      "get_cost": 0.10827010800000002,
      "put_cost": 0.008647325999999999,
      "storage_cost": 0.001249627397260274,
      "vm_cost": 0.411576,
      "total_cost": 0.5297430613972602,
      "get_latency": 656.2,
      "put_latency": 984.3000000000001,
      "iq1": [
        5,
        7,
        8
      ],
      "iq2": [
        5,
        7,
        8
      ],
      "iq3": [
        5,
        7,
        8
      ],
      "iq4": [
        5,
        7,
        8
      ]
    },
    {
      "id": 5,
      "protocol": "replication",
      "m": 5,
      "k": 1,
      "selected_dcs": [
        0,
        2,
        5,
        7,
        8
      ],
      "get_cost": 0.13532410800000003,
      "put_cost": 0.010807325999999997,
      "storage_cost": 0.0015619561643835616,
      "vm_cost": 0.411576,
      "total_cost": 0.5592693901643836,
      "get_latency": 656.2,
      "put_latency": 984.3000000000001,
      "iq1": [
        5,
        7,
        8
      ],
      "iq2": [
        5,
        7,
        8
      ],
      "iq3": [
        5,
        7,
        8
      ],
      "iq4": [
        5,
        7,
        8
      ]
    },
    {
      "id": 6,
      "protocol": "replication",
      "m": 5,
      "k": 1,
      "selected_dcs": [
        0,
        1,
        5,
        7,
        8
      ],
      "get_cost": 0.158488812,
      "put_cost": 0.012967253999999996,
      "storage_cost": 0.001940049315068493,
      "vm_cost": 0.414882,
      "total_cost": 0.5882781153150685,
      "get_latency": 551.0,
      "put_latency": 826.5,
      "iq1": [
        5,
        7,
        8
      ],
      "iq2": [
        5,
        7,
        8
      ],
      "iq3": [
        5,
        7,
        8
      ],
      "iq4": [
        5,
        7,
        8
      ]
    },
    {
      "id": 7,
      "protocol": "replication",
      "m": 5,
      "k": 1,
      "selected_dcs": [
        0,
        1,
        5,
        7,
        8
      ],
      "get_cost": 0.18489481200000005,
      "put_cost": 0.015127253999999996,
      "storage_cost": 0.00226333698630137,
      "vm_cost": 0.414882,
      "total_cost": 0.6171674029863015,
      "get_latency": 551.0,
      "put_latency": 826.5,
      "iq1": [
        5,
        7,
        8
      ],
      "iq2": [
        5,
        7,
        8
      ],
      "iq3": [
        5,
        7,
        8
      ],
      "iq4": [
        5,
        7,
        8
      ]
    },
    {
      "id": 8,
      "protocol": "replication",
      "m": 5,
      "k": 1,
      "selected_dcs": [
        0,
        1,
        5,
        7,
        8
      ],
      "get_cost": 0.211300812,
      "put_cost": 0.017287254000000002,
      "storage_cost": 0.0025866246575342463,
      "vm_cost": 0.414882,
      "total_cost": 0.6460566906575342,
      "get_latency": 551.0,
      "put_latency": 826.5,
      "iq1": [
        5,
        7,
        8
      ],
      "iq2": [
        5,
        7,
        8
      ],
      "iq3": [
        5,
        7,
        8
      ],
      "iq4": [
        5,
        7,
        8
      ]
    },
    {
      "id": 9,
      "protocol": "replication",
      "m": 5,
      "k": 1,
      "selected_dcs": [
        0,
        1,
        5,
        7,
        8
      ],
      "get_cost": 0.23770681200000002,
      "put_cost": 0.019447253999999994,
      "storage_cost": 0.002909912328767123,
      "vm_cost": 0.414882,
      "total_cost": 0.6749459783287671,
      "get_latency": 551.0,
      "put_latency": 826.5,
      "iq1": [
        5,
        7,
        8
      ],
      "iq2": [
        5,
        7,
        8
      ],
      "iq3": [
        5,
        7,
        8
      ],
      "iq4": [
        5,
        7,
        8
      ]
    },
    {
      "id": 10,
      "protocol": "replication",
      "m": 5,
      "k": 1,
      "selected_dcs": [
        0,
        1,
        5,
        7,
        8
      ],
      "get_cost": 0.264112812,
      "put_cost": 0.021607253999999992,
      "storage_cost": 0.0032332,
      "vm_cost": 0.414882,
      "total_cost": 0.703835266,
      "get_latency": 551.0,
      "put_latency": 826.5,
      "iq1": [
        5,
        7,
        8
      ],
      "iq2": [
        5,
        7,
        8
      ],
      "iq3": [
        5,
        7,
        8
      ],
      "iq4": [
        5,
        7,
        8
      ]
    },
    {
      "id": 11,
      "protocol": "replication",
      "m": 5,
      "k": 1,
      "selected_dcs": [
        0,
        1,
        5,
        7,
        8
      ],
      "get_cost": 0.290518812,
      "put_cost": 0.023767253999999998,
      "storage_cost": 0.0035564876712328767,
      "vm_cost": 0.414882,
      "total_cost": 0.7327245536712329,
      "get_latency": 551.0,
      "put_latency": 826.5,
      "iq1": [
        5,
        7,
        8
      ],
      "iq2": [
        5,
        7,
        8
      ],
      "iq3": [
        5,
        7,
        8
      ],
      "iq4": [
        5,
        7,
        8
      ]
    },
    {
      "id": 12,
      "protocol": "replication",
      "m": 5,
      "k": 1,
      "selected_dcs": [
        0,
        1,
        5,
        7,
        8
      ],
      "get_cost": 0.31692481200000006,
      "put_cost": 0.025927254,
      "storage_cost": 0.0038797753424657535,
      "vm_cost": 0.414882,
      "total_cost": 0.7616138413424658,
      "get_latency": 551.0,
      "put_latency": 826.5,
      "iq1": [
        5,
        7,
        8
      ],
      "iq2": [
        5,
        7,
        8
      ],
      "iq3": [
        5,
        7,
        8
      ],
      "iq4": [
        5,
        7,
        8
      ]
    },
    {
      "id": 13,
      "protocol": "replication",
      "m": 5,
      "k": 1,
      "selected_dcs": [
        0,
        1,
        5,
        7,
        8
      ],
      "get_cost": 0.34333081200000004,
      "put_cost": 0.02808725399999999,
      "storage_cost": 0.00420306301369863,
      "vm_cost": 0.414882,
      "total_cost": 0.7905031290136986,
      "get_latency": 551.0,
      "put_latency": 826.5,
      "iq1": [
        5,
        7,
        8
      ],
      "iq2": [
        5,
        7,
        8
      ],
      "iq3": [
        5,
        7,
        8
      ],
      "iq4": [
        5,
        7,
        8
      ]
    },
    {
      "id": 14,
      "protocol": "replication",
      "m": 5,
      "k": 1,
      "selected_dcs": [
        0,
        1,
        5,
        7,
        8
      ],
      "get_cost": 0.369736812,
      "put_cost": 0.03024725399999999,
      "storage_cost": 0.004526350684931507,
      "vm_cost": 0.414882,
      "total_cost": 0.8193924166849316,
      "get_latency": 551.0,
      "put_latency": 826.5,
      "iq1": [
        5,
        7,
        8
      ],
      "iq2": [
        5,
        7,
        8
      ],
      "iq3": [
        5,
        7,
        8
      ],
      "iq4": [
        5,
        7,
        8
      ]
    },
    {
      "id": 15,
      "protocol": "replication",
      "m": 5,
      "k": 1,
      "selected_dcs": [
        0,
        1,
        5,
        7,
        8
      ],
      "get_cost": 0.39614281199999996,
      "put_cost": 0.032407253999999996,
      "storage_cost": 0.004849638356164383,
      "vm_cost": 0.414882,
      "total_cost": 0.8482817043561643,
      "get_latency": 551.0,
      "put_latency": 826.5,
      "iq1": [
        5,
        7,
        8
      ],
      "iq2": [
        5,
        7,
        8
      ],
      "iq3": [
        5,
        7,
        8
      ],
      "iq4": [
        5,
        7,
        8
      ]
    },
    {
      "id": 16,
      "protocol": "replication",
      "m": 5,
      "k": 1,
      "selected_dcs": [
        0,
        1,
        5,
        7,
        8
      ],
      "get_cost": 0.42254881200000005,
      "put_cost": 0.03456725399999999,
      "storage_cost": 0.00517292602739726,
      "vm_cost": 0.414882,
      "total_cost": 0.8771709920273973,
      "get_latency": 551.0,
      "put_latency": 826.5,
      "iq1": [
        5,
        7,
        8
      ],
      "iq2": [
        5,
        7,
        8
      ],
      "iq3": [
        5,
        7,
        8
      ],
      "iq4": [
        5,
        7,
        8
      ]
    },
    {
      "id": 17,
      "protocol": "replication",
      "m": 5,
      "k": 1,
      "selected_dcs": [
        0,
        1,
        5,
        7,
        8
      ],
      "get_cost": 0.44895481200000004,
      "put_cost": 0.036727253999999994,
      "storage_cost": 0.005496213698630136,
      "vm_cost": 0.414882,
      "total_cost": 0.9060602796986301,
      "get_latency": 551.0,
      "put_latency": 826.5,
      "iq1": [
        5,
        7,
        8
      ],
      "iq2": [
        5,
        7,
        8
      ],
      "iq3": [
        5,
        7,
        8
      ],
      "iq4": [
        5,
        7,
        8
      ]
    },
    {
      "id": 18,
      "protocol": "replication",
      "m": 5,
      "k": 1,
      "selected_dcs": [
        0,
        1,
        5,
        7,
        8
      ],
      "get_cost": 0.475360812,
      "put_cost": 0.038887253999999996,
      "storage_cost": 0.005819501369863013,
      "vm_cost": 0.414882,
      "total_cost": 0.934949567369863,
      "get_latency": 551.0,
      "put_latency": 826.5,
      "iq1": [
        5,
        7,
        8
      ],
      "iq2": [
        5,
        7,
        8
      ],
      "iq3": [
        5,
        7,
        8
      ],
      "iq4": [
        5,
        7,
        8
      ]
    },
    {
      "id": 19,
      "protocol": "replication",
      "m": 5,
      "k": 1,
      "selected_dcs": [
        0,
        1,
        5,
        7,
        8
      ],
      "get_cost": 0.501766812,
      "put_cost": 0.041047253999999984,
      "storage_cost": 0.00614278904109589,
      "vm_cost": 0.414882,
      "total_cost": 0.9638388550410958,
      "get_latency": 551.0,
      "put_latency": 826.5,
      "iq1": [
        5,
        7,
        8
      ],
      "iq2": [
        5,
        7,
        8
      ],
      "iq3": [
        5,
        7,
        8
      ],
      "iq4": [
        5,
        7,
        8
      ]
    },
    {
      "id": 20,
      "protocol": "replication",
      "m": 5,
      "k": 1,
      "selected_dcs": [
        0,
        1,
        5,
        7,
        8
      ],
      "get_cost": 0.528172812,
      "put_cost": 0.043207253999999994,
      "storage_cost": 0.006466076712328767,
      "vm_cost": 0.414882,
      "total_cost": 0.9927281427123288,
      "get_latency": 551.0,
      "put_latency": 826.5,
      "iq1": [
        5,
        7,
        8
      ],
      "iq2": [
        5,
        7,
        8
      ],
      "iq3": [
        5,
        7,
        8
      ],
      "iq4": [
        5,
        7,
        8
      ]
    },
    {
      "id": 21,
      "protocol": "replication",
      "m": 5,
      "k": 1,
      "selected_dcs": [
        0,
        1,
        5,
        7,
        8
      ],
      "get_cost": 0.554578812,
      "put_cost": 0.04536725399999999,
      "storage_cost": 0.006789364383561643,
      "vm_cost": 0.414882,
      "total_cost": 1.0216174303835617,
      "get_latency": 551.0,
      "put_latency": 826.5,
      "iq1": [
        5,
        7,
        8
      ],
      "iq2": [
        5,
        7,
        8
      ],
      "iq3": [
        5,
        7,
        8
      ],
      "iq4": [
        5,
        7,
        8
      ]
    },
    {
      "id": 22,
      "protocol": "replication",
      "m": 5,
      "k": 1,
      "selected_dcs": [
        0,
        1,
        5,
        7,
        8
      ],
      "get_cost": 0.5809848120000001,
      "put_cost": 0.04752725399999999,
      "storage_cost": 0.007112652054794521,
      "vm_cost": 0.414882,
      "total_cost": 1.0505067180547947,
      "get_latency": 551.0,
      "put_latency": 826.5,
      "iq1": [
        5,
        7,
        8
      ],
      "iq2": [
        5,
        7,
        8
      ],
      "iq3": [
        5,
        7,
        8
      ],
      "iq4": [
        5,
        7,
        8
      ]
    },
    {
      "id": 23,
      "protocol": "replication",
      "m": 5,
      "k": 1,
      "selected_dcs": [
        0,
        1,
        5,
        7,
        8
      ],
      "get_cost": 0.607390812,
      "put_cost": 0.049687253999999986,
      "storage_cost": 0.007435939726027396,
      "vm_cost": 0.414882,
      "total_cost": 1.0793960057260272,
      "get_latency": 551.0,
      "put_latency": 826.5,
      "iq1": [
        5,
        7,
        8
      ],
      "iq2": [
        5,
        7,
        8
      ],
      "iq3": [
        5,
        7,
        8
      ],
      "iq4": [
        5,
        7,
        8
      ]
    },
    {
      "id": 24,
      "protocol": "replication",
      "m": 5,
      "k": 1,
      "selected_dcs": [
        0,
        1,
        5,
        7,
        8
      ],
      "get_cost": 0.633796812,
      "put_cost": 0.05184725399999999,
      "storage_cost": 0.007759227397260274,
      "vm_cost": 0.414882,
      "total_cost": 1.1082852933972602,
      "get_latency": 551.0,
      "put_latency": 826.5,
      "iq1": [
        5,
        7,
        8
      ],
      "iq2": [
        5,
        7,
        8
      ],
      "iq3": [
        5,
        7,
        8
      ],
      "iq4": [
        5,
        7,
        8
      ]
    },
    {
      "id": 25,
      "protocol": "replication",
      "m": 5,
      "k": 1,
      "selected_dcs": [
        0,
        1,
        5,
        7,
        8
      ],
      "get_cost": 0.6602028120000001,
      "put_cost": 0.05400725399999999,
      "storage_cost": 0.00808251506849315,
      "vm_cost": 0.414882,
      "total_cost": 1.1371745810684932,
      "get_latency": 551.0,
      "put_latency": 826.5,
      "iq1": [
        5,
        7,
        8
      ],
      "iq2": [
        5,
        7,
        8
      ],
      "iq3": [
        5,
        7,
        8
      ],
      "iq4": [
        5,
        7,
        8
      ]
    },
    {
      "id": 26,
      "protocol": "replication",
      "m": 5,
      "k": 1,
      "selected_dcs": [
        0,
        1,
        5,
        7,
        8
      ],
      "get_cost": 0.6866088120000001,
      "put_cost": 0.05616725399999999,
      "storage_cost": 0.008405802739726027,
      "vm_cost": 0.414882,
      "total_cost": 1.1660638687397262,
      "get_latency": 551.0,
      "put_latency": 826.5,
      "iq1": [
        5,
        7,
        8
      ],
      "iq2": [
        5,
        7,
        8
      ],
      "iq3": [
        5,
        7,
        8
      ],
      "iq4": [
        5,
        7,
        8
      ]
    },
    {
      "id": 27,
      "protocol": "replication",
      "m": 5,
      "k": 1,
      "selected_dcs": [
        0,
        1,
        5,
        7,
        8
      ],
      "get_cost": 0.713014812,
      "put_cost": 0.05832725399999999,
      "storage_cost": 0.008729090410958904,
      "vm_cost": 0.414882,
      "total_cost": 1.1949531564109588,
      "get_latency": 551.0,
      "put_latency": 826.5,
      "iq1": [
        5,
        7,
        8
      ],
      "iq2": [
        5,
        7,
        8
      ],
      "iq3": [
        5,
        7,
        8
      ],
      "iq4": [
        5,
        7,
        8
      ]
    },
    {
      "id": 28,
      "protocol": "replication",
      "m": 5,
      "k": 1,
      "selected_dcs": [
        0,
        1,
        5,
        7,
        8
      ],
      "get_cost": 0.7394208119999999,
      "put_cost": 0.060487253999999976,
      "storage_cost": 0.00905237808219178,
      "vm_cost": 0.414882,
      "total_cost": 1.2238424440821916,
      "get_latency": 551.0,
      "put_latency": 826.5,
      "iq1": [
        5,
        7,
        8
      ],
      "iq2": [
        5,
        7,
        8
      ],
      "iq3": [
        5,
        7,
        8
      ],
      "iq4": [
        5,
        7,
        8
      ]
    },
    {
      "id": 29,
      "protocol": "replication",
      "m": 5,
      "k": 1,
      "selected_dcs": [
        0,
        1,
        5,
        7,
        8
      ],
      "get_cost": 0.765826812,
      "put_cost": 0.06264725399999999,
      "storage_cost": 0.009375665753424658,
      "vm_cost": 0.414882,
      "total_cost": 1.2527317317534248,
      "get_latency": 551.0,
      "put_latency": 826.5,
      "iq1": [
        5,
        7,
        8
      ],
      "iq2": [
        5,
        7,
        8
      ],
      "iq3": [
        5,
        7,
        8
      ],
      "iq4": [
        5,
        7,
        8
      ]
    },
    {
      "id": 30,
      "protocol": "replication",
      "m": 5,
      "k": 1,
      "selected_dcs": [
        0,
        1,
        5,
        7,
        8
      ],
      "get_cost": 0.792232812,
      "put_cost": 0.06480725399999997,
      "storage_cost": 0.009698953424657535,
      "vm_cost": 0.414882,
      "total_cost": 1.2816210194246573,
      "get_latency": 551.0,
      "put_latency": 826.5,
      "iq1": [
        5,
        7,
        8
      ],
      "iq2": [
        5,
        7,
        8
      ],
      "iq3": [
        5,
        7,
        8
      ],
      "iq4": [
        5,
        7,
        8
      ]
    },
    {
      "id": 31,
      "protocol": "replication",
      "m": 5,
      "k": 1,
      "selected_dcs": [
        0,
        1,
        5,
        7,
        8
      ],
      "get_cost": 0.8186388119999999,
      "put_cost": 0.06696725399999998,
      "storage_cost": 0.010022241095890408,
      "vm_cost": 0.414882,
      "total_cost": 1.3105103070958903,
      "get_latency": 551.0,
      "put_latency": 826.5,
      "iq1": [
        5,
        7,
        8
      ],
      "iq2": [
        5,
        7,
        8
      ],
      "iq3": [
        5,
        7,
        8
      ],
      "iq4": [
        5,
        7,
        8
      ]
    },
    {
      "id": 32,
      "protocol": "replication",
      "m": 5,
      "k": 1,
      "selected_dcs": [
        0,
        1,
        5,
        7,
        8
      ],
      "get_cost": 0.8450448119999999,
      "put_cost": 0.06912725399999999,
      "storage_cost": 0.010345528767123286,
      "vm_cost": 0.414882,
      "total_cost": 1.3393995947671231,
      "get_latency": 551.0,
      "put_latency": 826.5,
      "iq1": [
        5,
        7,
        8
      ],
      "iq2": [
        5,
        7,
        8
      ],
      "iq3": [
        5,
        7,
        8
      ],
      "iq4": [
        5,
        7,
        8
      ]
    },
    {
      "id": 33,
      "protocol": "replication",
      "m": 5,
      "k": 1,
      "selected_dcs": [
        0,
        1,
        5,
        7,
        8
      ],
      "get_cost": 0.8714508119999999,
      "put_cost": 0.07128725399999997,
      "storage_cost": 0.010668816438356163,
      "vm_cost": 0.414882,
      "total_cost": 1.368288882438356,
      "get_latency": 551.0,
      "put_latency": 826.5,
      "iq1": [
        5,
        7,
        8
      ],
      "iq2": [
        5,
        7,
        8
      ],
      "iq3": [
        5,
        7,
        8
      ],
      "iq4": [
        5,
        7,
        8
      ]
    },
    {
      "id": 34,
      "protocol": "replication",
      "m": 5,
      "k": 1,
      "selected_dcs": [
        0,
        1,
        5,
        7,
        8
      ],
      "get_cost": 0.8978568119999999,
      "put_cost": 0.07344725399999999,
      "storage_cost": 0.010992104109589042,
      "vm_cost": 0.414882,
      "total_cost": 1.397178170109589,
      "get_latency": 551.0,
      "put_latency": 826.5,
      "iq1": [
        5,
        7,
        8
      ],
      "iq2": [
        5,
        7,
        8
      ],
      "iq3": [
        5,
        7,
        8
      ],
      "iq4": [
        5,
        7,
        8
      ]
    },
    {
      "id": 35,
      "protocol": "replication",
      "m": 5,
      "k": 1,
      "selected_dcs": [
        0,
        1,
        5,
        7,
        8
      ],
      "get_cost": 0.9242628119999998,
      "put_cost": 0.07560725399999998,
      "storage_cost": 0.011315391780821917,
      "vm_cost": 0.414882,
      "total_cost": 1.4260674577808217,
      "get_latency": 551.0,
      "put_latency": 826.5,
      "iq1": [
        5,
        7,
        8
      ],
      "iq2": [
        5,
        7,
        8
      ],
      "iq3": [
        5,
        7,
        8
      ],
      "iq4": [
        5,
        7,
        8
      ]
    },
    {
      "id": 36,
      "protocol": "replication",
      "m": 5,
      "k": 1,
      "selected_dcs": [
        0,
        1,
        5,
        7,
        8
      ],
      "get_cost": 0.9506688119999999,
      "put_cost": 0.07776725399999998,
      "storage_cost": 0.011638679452054795,
      "vm_cost": 0.414882,
      "total_cost": 1.4549567454520547,
      "get_latency": 551.0,
      "put_latency": 826.5,
      "iq1": [
        5,
        7,
        8
      ],
      "iq2": [
        5,
        7,
        8
      ],
      "iq3": [
        5,
        7,
        8
      ],
      "iq4": [
        5,
        7,
        8
      ]
    },
    {
      "id": 37,
      "protocol": "replication",
      "m": 5,
      "k": 1,
      "selected_dcs": [
        0,
        1,
        5,
        7,
        8
      ],
      "get_cost": 0.977074812,
      "put_cost": 0.07992725399999999,
      "storage_cost": 0.01196196712328767,
      "vm_cost": 0.414882,
      "total_cost": 1.4838460331232874,
      "get_latency": 551.0,
      "put_latency": 826.5,
      "iq1": [
        5,
        7,
        8
      ],
      "iq2": [
        5,
        7,
        8
      ],
      "iq3": [
        5,
        7,
        8
      ],
      "iq4": [
        5,
        7,
        8
      ]
    },
    {
      "id": 38,
      "protocol": "replication",
      "m": 5,
      "k": 1,
      "selected_dcs": [
        0,
        1,
        5,
        7,
        8
      ],
      "get_cost": 1.0034808119999998,
      "put_cost": 0.08208725399999998,
      "storage_cost": 0.012285254794520547,
      "vm_cost": 0.414882,
      "total_cost": 1.5127353207945202,
      "get_latency": 551.0,
      "put_latency": 826.5,
      "iq1": [
        5,
        7,
        8
      ],
      "iq2": [
        5,
        7,
        8
      ],
      "iq3": [
        5,
        7,
        8
      ],
      "iq4": [
        5,
        7,
        8
      ]
    },
    {
      "id": 39,
      "protocol": "replication",
      "m": 5,
      "k": 1,
      "selected_dcs": [
        0,
        1,
        5,
        7,
        8
      ],
      "get_cost": 1.0298868120000002,
      "put_cost": 0.08424725399999998,
      "storage_cost": 0.012608542465753424,
      "vm_cost": 0.414882,
      "total_cost": 1.5416246084657534,
      "get_latency": 551.0,
      "put_latency": 826.5,
      "iq1": [
        5,
        7,
        8
      ],
      "iq2": [
        5,
        7,
        8
      ],
      "iq3": [
        5,
        7,
        8
      ],
      "iq4": [
        5,
        7,
        8
      ]
    },
    {
      "id": 40,
      "protocol": "replication",
      "m": 5,
      "k": 1,
      "selected_dcs": [
        0,
        1,
        5,
        7,
        8
      ],
      "get_cost": 1.0562928120000001,
      "put_cost": 0.08640725399999998,
      "storage_cost": 0.012931830136986299,
      "vm_cost": 0.414882,
      "total_cost": 1.5705138961369864,
      "get_latency": 551.0,
      "put_latency": 826.5,
      "iq1": [
        5,
        7,
        8
      ],
      "iq2": [
        5,
        7,
        8
      ],
      "iq3": [
        5,
        7,
        8
      ],
      "iq4": [
        5,
        7,
        8
      ]
    },
    {
      "id": 41,
      "protocol": "replication",
      "m": 5,
      "k": 1,
      "selected_dcs": [
        0,
        1,
        5,
        7,
        8
      ],
      "get_cost": 1.082698812,
      "put_cost": 0.08856725399999998,
      "storage_cost": 0.013255117808219178,
      "vm_cost": 0.414882,
      "total_cost": 1.5994031838082192,
      "get_latency": 551.0,
      "put_latency": 826.5,
      "iq1": [
        5,
        7,
        8
      ],
      "iq2": [
        5,
        7,
        8
      ],
      "iq3": [
        5,
        7,
        8
      ],
      "iq4": [
        5,
        7,
        8
      ]
    },
    {
      "id": 42,
      "protocol": "replication",
      "m": 5,
      "k": 1,
      "selected_dcs": [
        0,
        1,
        5,
        7,
        8
      ],
      "get_cost": 1.109104812,
      "put_cost": 0.09072725399999998,
      "storage_cost": 0.013578405479452054,
      "vm_cost": 0.414882,
      "total_cost": 1.628292471479452,
      "get_latency": 551.0,
      "put_latency": 826.5,
      "iq1": [
        5,
        7,
        8
      ],
      "iq2": [
        5,
        7,
        8
      ],
      "iq3": [
        5,
        7,
        8
      ],
      "iq4": [
        5,
        7,
        8
      ]
    },
    {
      "id": 43,
      "protocol": "replication",
      "m": 5,
      "k": 1,
      "selected_dcs": [
        0,
        1,
        5,
        7,
        8
      ],
      "get_cost": 1.1355108120000001,
      "put_cost": 0.09288725399999997,
      "storage_cost": 0.01390169315068493,
      "vm_cost": 0.414882,
      "total_cost": 1.657181759150685,
      "get_latency": 551.0,
      "put_latency": 826.5,
      "iq1": [
        5,
        7,
        8
      ],
      "iq2": [
        5,
        7,
        8
      ],
      "iq3": [
        5,
        7,
        8
      ],
      "iq4": [
        5,
        7,
        8
      ]
    },
    {
      "id": 44,
      "protocol": "replication",
      "m": 5,
      "k": 1,
      "selected_dcs": [
        0,
        1,
        5,
        7,
        8
      ],
      "get_cost": 1.161916812,
      "put_cost": 0.09504725399999998,
      "storage_cost": 0.014224980821917808,
      "vm_cost": 0.414882,
      "total_cost": 1.6860710468219178,
      "get_latency": 551.0,
      "put_latency": 826.5,
      "iq1": [
        5,
        7,
        8
      ],
      "iq2": [
        5,
        7,
        8
      ],
      "iq3": [
        5,
        7,
        8
      ],
      "iq4": [
        5,
        7,
        8
      ]
    },
    {
      "id": 45,
      "protocol": "replication",
      "m": 5,
      "k": 1,
      "selected_dcs": [
        0,
        1,
        5,
        7,
        8
      ],
      "get_cost": 1.188322812,
      "put_cost": 0.09720725399999998,
      "storage_cost": 0.014548268493150685,
      "vm_cost": 0.414882,
      "total_cost": 1.7149603344931506,
      "get_latency": 551.0,
      "put_latency": 826.5,
      "iq1": [
        5,
        7,
        8
      ],
      "iq2": [
        5,
        7,
        8
      ],
      "iq3": [
        5,
        7,
        8
      ],
      "iq4": [
        5,
        7,
        8
      ]
    },
    {
      "id": 46,
      "protocol": "replication",
      "m": 5,
      "k": 1,
      "selected_dcs": [
        0,
        1,
        5,
        7,
        8
      ],
      "get_cost": 1.2147288120000002,
      "put_cost": 0.099367254,
      "storage_cost": 0.014871556164383562,
      "vm_cost": 0.414882,
      "total_cost": 1.7438496221643836,
      "get_latency": 551.0,
      "put_latency": 826.5,
      "iq1": [
        5,
        7,
        8
      ],
      "iq2": [
        5,
        7,
        8
      ],
      "iq3": [
        5,
        7,
        8
      ],
      "iq4": [
        5,
        7,
        8
      ]
    },
    {
      "id": 47,
      "protocol": "replication",
      "m": 5,
      "k": 1,
      "selected_dcs": [
        0,
        1,
        5,
        7,
        8
      ],
      "get_cost": 1.241134812,
      "put_cost": 0.10152725399999998,
      "storage_cost": 0.015194843835616437,
      "vm_cost": 0.414882,
      "total_cost": 1.7727389098356165,
      "get_latency": 551.0,
      "put_latency": 826.5,
      "iq1": [
        5,
        7,
        8
      ],
      "iq2": [
        5,
        7,
        8
      ],
      "iq3": [
        5,
        7,
        8
      ],
      "iq4": [
        5,
        7,
        8
      ]
    },
    {
      "id": 48,
      "protocol": "replication",
      "m": 5,
      "k": 1,
      "selected_dcs": [
        0,
        1,
        5,
        7,
        8
      ],
      "get_cost": 1.2675408119999998,
      "put_cost": 0.10368725399999998,
      "storage_cost": 0.015518131506849314,
      "vm_cost": 0.414882,
      "total_cost": 1.801628197506849,
      "get_latency": 551.0,
      "put_latency": 826.5,
      "iq1": [
        5,
        7,
        8
      ],
      "iq2": [
        5,
        7,
        8
      ],
      "iq3": [
        5,
        7,
        8
      ],
      "iq4": [
        5,
        7,
        8
      ]
    },
    {
      "id": 49,
      "protocol": "replication",
      "m": 5,
      "k": 1,
      "selected_dcs": [
        0,
        1,
        5,
        7,
        8
      ],
      "get_cost": 1.293946812,
      "put_cost": 0.10584725399999999,
      "storage_cost": 0.01584141917808219,
      "vm_cost": 0.414882,
      "total_cost": 1.830517485178082,
      "get_latency": 551.0,
      "put_latency": 826.5,
      "iq1": [
        5,
        7,
        8
      ],
      "iq2": [
        5,
        7,
        8
      ],
      "iq3": [
        5,
        7,
        8
      ],
      "iq4": [
        5,
        7,
        8
      ]
    },
    {
      "id": 50,
      "protocol": "replication",
      "m": 5,
      "k": 1,
      "selected_dcs": [
        0,
        1,
        5,
        7,
        8
      ],
      "get_cost": 1.3203528119999999,
      "put_cost": 0.10800725399999996,
      "storage_cost": 0.016164706849315067,
      "vm_cost": 0.414882,
      "total_cost": 1.8594067728493149,
      "get_latency": 551.0,
      "put_latency": 826.5,
      "iq1": [
        5,
        7,
        8
      ],
      "iq2": [
        5,
        7,
        8
      ],
      "iq3": [
        5,
        7,
        8
      ],
      "iq4": [
        5,
        7,
        8
      ]
    },
    {
      "id": 51,
      "protocol": "replication",
      "m": 5,
      "k": 1,
      "selected_dcs": [
        0,
        1,
        5,
        7,
        8
      ],
      "get_cost": 1.346758812,
      "put_cost": 0.11016725399999996,
      "storage_cost": 0.016487994520547947,
      "vm_cost": 0.414882,
      "total_cost": 1.888296060520548,
      "get_latency": 551.0,
      "put_latency": 826.5,
      "iq1": [
        5,
        7,
        8
      ],
      "iq2": [
        5,
        7,
        8
      ],
      "iq3": [
        5,
        7,
        8
      ],
      "iq4": [
        5,
        7,
        8
      ]
    },
    {
      "id": 52,
      "protocol": "replication",
      "m": 5,
      "k": 1,
      "selected_dcs": [
        0,
        1,
        5,
        7,
        8
      ],
      "get_cost": 1.373164812,
      "put_cost": 0.11232725399999997,
      "storage_cost": 0.01681128219178082,
      "vm_cost": 0.414882,
      "total_cost": 1.9171853481917807,
      "get_latency": 551.0,
      "put_latency": 826.5,
      "iq1": [
        5,
        7,
        8
      ],
      "iq2": [
        5,
        7,
        8
      ],
      "iq3": [
        5,
        7,
        8
      ],
      "iq4": [
        5,
        7,
        8
      ]
    },
    {
      "id": 53,
      "protocol": "replication",
      "m": 5,
      "k": 1,
      "selected_dcs": [
        0,
        1,
        5,
        7,
        8
      ],
      "get_cost": 1.3995708119999999,
      "put_cost": 0.11448725399999997,
      "storage_cost": 0.017134569863013697,
      "vm_cost": 0.414882,
      "total_cost": 1.9460746358630134,
      "get_latency": 551.0,
      "put_latency": 826.5,
      "iq1": [
        5,
        7,
        8
      ],
      "iq2": [
        5,
        7,
        8
      ],
      "iq3": [
        5,
        7,
        8
      ],
      "iq4": [
        5,
        7,
        8
      ]
    },
    {
      "id": 54,
      "protocol": "replication",
      "m": 5,
      "k": 1,
      "selected_dcs": [
        0,
        1,
        5,
        7,
        8
      ],
      "get_cost": 1.425976812,
      "put_cost": 0.11664725399999998,
      "storage_cost": 0.017457857534246574,
      "vm_cost": 0.414882,
      "total_cost": 1.9749639235342467,
      "get_latency": 551.0,
      "put_latency": 826.5,
      "iq1": [
        5,
        7,
        8
      ],
      "iq2": [
        5,
        7,
        8
      ],
      "iq3": [
        5,
        7,
        8
      ],
      "iq4": [
        5,
        7,
        8
      ]
    },
    {
      "id": 55,
      "protocol": "replication",
      "m": 5,
      "k": 1,
      "selected_dcs": [
        0,
        1,
        5,
        7,
        8
      ],
      "get_cost": 1.452382812,
      "put_cost": 0.11880725399999997,
      "storage_cost": 0.017781145205479448,
      "vm_cost": 0.414882,
      "total_cost": 2.003853211205479,
      "get_latency": 551.0,
      "put_latency": 826.5,
      "iq1": [
        5,
        7,
        8
      ],
      "iq2": [
        5,
        7,
        8
      ],
      "iq3": [
        5,
        7,
        8
      ],
      "iq4": [
        5,
        7,
        8
      ]
    },
    {
      "id": 56,
      "protocol": "replication",
      "m": 5,
      "k": 1,
      "selected_dcs": [
        0,
        1,
        5,
        7,
        8
      ],
      "get_cost": 1.4787888120000001,
      "put_cost": 0.12096725399999998,
      "storage_cost": 0.018104432876712328,
      "vm_cost": 0.414882,
      "total_cost": 2.032742498876712,
      "get_latency": 551.0,
      "put_latency": 826.5,
      "iq1": [
        5,
        7,
        8
      ],
      "iq2": [
        5,
        7,
        8
      ],
      "iq3": [
        5,
        7,
        8
      ],
      "iq4": [
        5,
        7,
        8
      ]
    },
    {
      "id": 57,
      "protocol": "replication",
      "m": 5,
      "k": 1,
      "selected_dcs": [
        0,
        1,
        5,
        7,
        8
      ],
      "get_cost": 1.505194812,
      "put_cost": 0.12312725399999996,
      "storage_cost": 0.018427720547945205,
      "vm_cost": 0.414882,
      "total_cost": 2.061631786547945,
      "get_latency": 551.0,
      "put_latency": 826.5,
      "iq1": [
        5,
        7,
        8
      ],
      "iq2": [
        5,
        7,
        8
      ],
      "iq3": [
        5,
        7,
        8
      ],
      "iq4": [
        5,
        7,
        8
      ]
    },
    {
      "id": 58,
      "protocol": "replication",
      "m": 5,
      "k": 1,
      "selected_dcs": [
        0,
        1,
        5,
        7,
        8
      ],
      "get_cost": 1.5316008120000002,
      "put_cost": 0.125287254,
      "storage_cost": 0.01875100821917808,
      "vm_cost": 0.414882,
      "total_cost": 2.090521074219178,
      "get_latency": 551.0,
      "put_latency": 826.5,
      "iq1": [
        5,
        7,
        8
      ],
      "iq2": [
        5,
        7,
        8
      ],
      "iq3": [
        5,
        7,
        8
      ],
      "iq4": [
        5,
        7,
        8
      ]
    },
    {
      "id": 59,
      "protocol": "replication",
      "m": 5,
      "k": 1,
      "selected_dcs": [
        0,
        1,
        5,
        7,
        8
      ],
      "get_cost": 1.5580068120000004,
      "put_cost": 0.12744725399999998,
      "storage_cost": 0.01907429589041096,
      "vm_cost": 0.414882,
      "total_cost": 2.119410361890411,
      "get_latency": 551.0,
      "put_latency": 826.5,
      "iq1": [
        5,
        7,
        8
      ],
      "iq2": [
        5,
        7,
        8
      ],
      "iq3": [
        5,
        7,
        8
      ],
      "iq4": [
        5,
        7,
        8
      ]
    },
    {
      "id": 60,
      "protocol": "replication",
      "m": 5,
      "k": 1,
      "selected_dcs": [
        0,
        1,
        5,
        7,
        8
      ],
      "get_cost": 1.584412812,
      "put_cost": 0.12960725399999998,
      "storage_cost": 0.019397583561643835,
      "vm_cost": 0.414882,
      "total_cost": 2.1482996495616438,
      "get_latency": 551.0,
      "put_latency": 826.5,
      "iq1": [
        5,
        7,
        8
      ],
      "iq2": [
        5,
        7,
        8
      ],
      "iq3": [
        5,
        7,
        8
      ],
      "iq4": [
        5,
        7,
        8
      ]
    },
    {
      "id": 61,
      "protocol": "replication",
      "m": 5,
      "k": 1,
      "selected_dcs": [
        0,
        1,
        5,
        7,
        8
      ],
      "get_cost": 1.6108188120000002,
      "put_cost": 0.13176725399999997,
      "storage_cost": 0.019720871232876712,
      "vm_cost": 0.414882,
      "total_cost": 2.1771889372328768,
      "get_latency": 551.0,
      "put_latency": 826.5,
      "iq1": [
        5,
        7,
        8
      ],
      "iq2": [
        5,
        7,
        8
      ],
      "iq3": [
        5,
        7,
        8
      ],
      "iq4": [
        5,
        7,
        8
      ]
    },
    {
      "id": 62,
      "protocol": "replication",
      "m": 5,
      "k": 1,
      "selected_dcs": [
        0,
        1,
        5,
        7,
        8
      ],
      "get_cost": 1.6372248120000001,
      "put_cost": 0.13392725399999997,
      "storage_cost": 0.02004415890410959,
      "vm_cost": 0.414882,
      "total_cost": 2.2060782249041098,
      "get_latency": 551.0,
      "put_latency": 826.5,
      "iq1": [
        5,
        7,
        8
      ],
      "iq2": [
        5,
        7,
        8
      ],
      "iq3": [
        5,
        7,
        8
      ],
      "iq4": [
        5,
        7,
        8
      ]
    },
    {
      "id": 63,
      "protocol": "replication",
      "m": 5,
      "k": 1,
      "selected_dcs": [
        0,
        1,
        5,
        7,
        8
      ],
      "get_cost": 1.6636308120000003,
      "put_cost": 0.136087254,
      "storage_cost": 0.020367446575342465,
      "vm_cost": 0.414882,
      "total_cost": 2.2349675125753428,
      "get_latency": 551.0,
      "put_latency": 826.5,
      "iq1": [
        5,
        7,
        8
      ],
      "iq2": [
        5,
        7,
        8
      ],
      "iq3": [
        5,
        7,
        8
      ],
      "iq4": [
        5,
        7,
        8
      ]
    },
    {
      "id": 64,
      "protocol": "replication",
      "m": 5,
      "k": 1,
      "selected_dcs": [
        0,
        1,
        5,
        7,
        8
      ],
      "get_cost": 1.690036812,
      "put_cost": 0.13824725399999996,
      "storage_cost": 0.02069073424657534,
      "vm_cost": 0.414882,
      "total_cost": 2.2638568002465753,
      "get_latency": 551.0,
      "put_latency": 826.5,
      "iq1": [
        5,
        7,
        8
      ],
      "iq2": [
        5,
        7,
        8
      ],
      "iq3": [
        5,
        7,
        8
      ],
      "iq4": [
        5,
        7,
        8
      ]
    },
    {
      "id": 65,
      "protocol": "replication",
      "m": 5,
      "k": 1,
      "selected_dcs": [
        0,
        1,
        5,
        7,
        8
      ],
      "get_cost": 1.716442812,
      "put_cost": 0.14040725399999998,
      "storage_cost": 0.021014021917808216,
      "vm_cost": 0.414882,
      "total_cost": 2.2927460879178083,
      "get_latency": 551.0,
      "put_latency": 826.5,
      "iq1": [
        5,
        7,
        8
      ],
      "iq2": [
        5,
        7,
        8
      ],
      "iq3": [
        5,
        7,
        8
      ],
      "iq4": [
        5,
        7,
        8
      ]
    },
    {
      "id": 66,
      "protocol": "replication",
      "m": 5,
      "k": 1,
      "selected_dcs": [
        0,
        1,
        5,
        7,
        8
      ],
      "get_cost": 1.7428488119999996,
      "put_cost": 0.14256725399999998,
      "storage_cost": 0.021337309589041092,
      "vm_cost": 0.414882,
      "total_cost": 2.3216353755890404,
      "get_latency": 551.0,
      "put_latency": 826.5,
      "iq1": [
        5,
        7,
        8
      ],
      "iq2": [
        5,
        7,
        8
      ],
      "iq3": [
        5,
        7,
        8
      ],
      "iq4": [
        5,
        7,
        8
      ]
    },
    {
      "id": 67,
      "protocol": "replication",
      "m": 5,
      "k": 1,
      "selected_dcs": [
        0,
        1,
        5,
        7,
        8
      ],
      "get_cost": 1.769254812,
      "put_cost": 0.144727254,
      "storage_cost": 0.021660597260273973,
      "vm_cost": 0.414882,
      "total_cost": 2.350524663260274,
      "get_latency": 551.0,
      "put_latency": 826.5,
      "iq1": [
        5,
        7,
        8
      ],
      "iq2": [
        5,
        7,
        8
      ],
      "iq3": [
        5,
        7,
        8
      ],
      "iq4": [
        5,
        7,
        8
      ]
    },
    {
      "id": 68,
      "protocol": "replication",
      "m": 5,
      "k": 1,
      "selected_dcs": [
        0,
        1,
        5,
        7,
        8
      ],
      "get_cost": 1.7956608119999997,
      "put_cost": 0.14688725399999997,
      "storage_cost": 0.02198388493150685,
      "vm_cost": 0.414882,
      "total_cost": 2.3794139509315064,
      "get_latency": 551.0,
      "put_latency": 826.5,
      "iq1": [
        5,
        7,
        8
      ],
      "iq2": [
        5,
        7,
        8
      ],
      "iq3": [
        5,
        7,
        8
      ],
      "iq4": [
        5,
        7,
        8
      ]
    },
    {
      "id": 69,
      "protocol": "replication",
      "m": 5,
      "k": 1,
      "selected_dcs": [
        0,
        1,
        5,
        7,
        8
      ],
      "get_cost": 1.822066812,
      "put_cost": 0.149047254,
      "storage_cost": 0.022307172602739726,
      "vm_cost": 0.414882,
      "total_cost": 2.40830323860274,
      "get_latency": 551.0,
      "put_latency": 826.5,
      "iq1": [
        5,
        7,
        8
      ],
      "iq2": [
        5,
        7,
        8
      ],
      "iq3": [
        5,
        7,
        8
      ],
      "iq4": [
        5,
        7,
        8
      ]
    },
    {
      "id": 70,
      "protocol": "replication",
      "m": 5,
      "k": 1,
      "selected_dcs": [
        0,
        1,
        5,
        7,
        8
      ],
      "get_cost": 1.8484728119999998,
      "put_cost": 0.15120725399999996,
      "storage_cost": 0.0226304602739726,
      "vm_cost": 0.414882,
      "total_cost": 2.4371925262739724,
      "get_latency": 551.0,
      "put_latency": 826.5,
      "iq1": [
        5,
        7,
        8
      ],
      "iq2": [
        5,
        7,
        8
      ],
      "iq3": [
        5,
        7,
        8
      ],
      "iq4": [
        5,
        7,
        8
      ]
    },
    {
      "id": 71,
      "protocol": "replication",
      "m": 5,
      "k": 1,
      "selected_dcs": [
        0,
        1,
        5,
        7,
        8
      ],
      "get_cost": 1.874878812,
      "put_cost": 0.15336725399999995,
      "storage_cost": 0.022953747945205473,
      "vm_cost": 0.414882,
      "total_cost": 2.4660818139452054,
      "get_latency": 551.0,
      "put_latency": 826.5,
      "iq1": [
        5,
        7,
        8
      ],
      "iq2": [
        5,
        7,
        8
      ],
      "iq3": [
        5,
        7,
        8
      ],
      "iq4": [
        5,
        7,
        8
      ]
    },
    {
      "id": 72,
      "protocol": "replication",
      "m": 5,
      "k": 1,
      "selected_dcs": [
        0,
        1,
        5,
        7,
        8
      ],
      "get_cost": 1.901284812,
      "put_cost": 0.155527254,
      "storage_cost": 0.023277035616438357,
      "vm_cost": 0.414882,
      "total_cost": 2.4949711016164384,
      "get_latency": 551.0,
      "put_latency": 826.5,
      "iq1": [
        5,
        7,
        8
      ],
      "iq2": [
        5,
        7,
        8
      ],
      "iq3": [
        5,
        7,
        8
      ],
      "iq4": [
        5,
        7,
        8
      ]
    },
    {
      "id": 73,
      "protocol": "replication",
      "m": 5,
      "k": 1,
      "selected_dcs": [
        0,
        1,
        5,
        7,
        8
      ],
      "get_cost": 1.9276908119999998,
      "put_cost": 0.15768725399999994,
      "storage_cost": 0.02360032328767123,
      "vm_cost": 0.414882,
      "total_cost": 2.523860389287671,
      "get_latency": 551.0,
      "put_latency": 826.5,
      "iq1": [
        5,
        7,
        8
      ],
      "iq2": [
        5,
        7,
        8
      ],
      "iq3": [
        5,
        7,
        8
      ],
      "iq4": [
        5,
        7,
        8
      ]
    },
    {
      "id": 74,
      "protocol": "replication",
      "m": 5,
      "k": 1,
      "selected_dcs": [
        0,
        1,
        5,
        7,
        8
      ],
      "get_cost": 1.9540968120000002,
      "put_cost": 0.15984725399999997,
      "storage_cost": 0.023923610958904107,
      "vm_cost": 0.414882,
      "total_cost": 2.5527496769589044,
      "get_latency": 551.0,
      "put_latency": 826.5,
      "iq1": [
        5,
        7,
        8
      ],
      "iq2": [
        5,
        7,
        8
      ],
      "iq3": [
        5,
        7,
        8
      ],
      "iq4": [
        5,
        7,
        8
      ]
    },
    {
      "id": 75,
      "protocol": "replication",
      "m": 5,
      "k": 1,
      "selected_dcs": [
        0,
        1,
        5,
        7,
        8
      ],
      "get_cost": 1.980502812,
      "put_cost": 0.16200725399999993,
      "storage_cost": 0.024246898630136984,
      "vm_cost": 0.414882,
      "total_cost": 2.581638964630137,
      "get_latency": 551.0,
      "put_latency": 826.5,
      "iq1": [
        5,
        7,
        8
      ],
      "iq2": [
        5,
        7,
        8
      ],
      "iq3": [
        5,
        7,
        8
      ],
      "iq4": [
        5,
        7,
        8
      ]
    },
    {
      "id": 76,
      "protocol": "replication",
      "m": 5,
      "k": 1,
      "selected_dcs": [
        0,
        1,
        5,
        7,
        8
      ],
      "get_cost": 2.006908812,
      "put_cost": 0.164167254,
      "storage_cost": 0.024570186301369864,
      "vm_cost": 0.414882,
      "total_cost": 2.6105282523013695,
      "get_latency": 551.0,
      "put_latency": 826.5,
      "iq1": [
        5,
        7,
        8
      ],
      "iq2": [
        5,
        7,
        8
      ],
      "iq3": [
        5,
        7,
        8
      ],
      "iq4": [
        5,
        7,
        8
      ]
    },
    {
      "id": 77,
      "protocol": "replication",
      "m": 5,
      "k": 1,
      "selected_dcs": [
        0,
        1,
        5,
        7,
        8
      ],
      "get_cost": 2.033314812,
      "put_cost": 0.16632725399999995,
      "storage_cost": 0.02489347397260274,
      "vm_cost": 0.414882,
      "total_cost": 2.6394175399726025,
      "get_latency": 551.0,
      "put_latency": 826.5,
      "iq1": [
        5,
        7,
        8
      ],
      "iq2": [
        5,
        7,
        8
      ],
      "iq3": [
        5,
        7,
        8
      ],
      "iq4": [
        5,
        7,
        8
      ]
    },
    {
      "id": 78,
      "protocol": "replication",
      "m": 5,
      "k": 1,
      "selected_dcs": [
        0,
        1,
        5,
        7,
        8
      ],
      "get_cost": 2.0597208120000006,
      "put_cost": 0.168487254,
      "storage_cost": 0.025216761643835614,
      "vm_cost": 0.414882,
      "total_cost": 2.668306827643836,
      "get_latency": 551.0,
      "put_latency": 826.5,
      "iq1": [
        5,
        7,
        8
      ],
      "iq2": [
        5,
        7,
        8
      ],
      "iq3": [
        5,
        7,
        8
      ],
      "iq4": [
        5,
        7,
        8
      ]
    },
    {
      "id": 79,
      "protocol": "replication",
      "m": 5,
      "k": 1,
      "selected_dcs": [
        0,
        1,
        5,
        7,
        8
      ],
      "get_cost": 2.0861268120000003,
      "put_cost": 0.17064725399999994,
      "storage_cost": 0.02554004931506849,
      "vm_cost": 0.414882,
      "total_cost": 2.6971961153150685,
      "get_latency": 551.0,
      "put_latency": 826.5,
      "iq1": [
        5,
        7,
        8
      ],
      "iq2": [
        5,
        7,
        8
      ],
      "iq3": [
        5,
        7,
        8
      ],
      "iq4": [
        5,
        7,
        8
      ]
    },
    {
      "id": 80,
      "protocol": "replication",
      "m": 5,
      "k": 1,
      "selected_dcs": [
        0,
        1,
        5,
        7,
        8
      ],
      "get_cost": 2.112532812,
      "put_cost": 0.17280725399999997,
      "storage_cost": 0.025863336986301364,
      "vm_cost": 0.414882,
      "total_cost": 2.726085402986301,
      "get_latency": 551.0,
      "put_latency": 826.5,
      "iq1": [
        5,
        7,
        8
      ],
      "iq2": [
        5,
        7,
        8
      ],
      "iq3": [
        5,
        7,
        8
      ],
      "iq4": [
        5,
        7,
        8
      ]
    },
    {
      "id": 81,
      "protocol": "replication",
      "m": 5,
      "k": 1,
      "selected_dcs": [
        0,
        1,
        5,
        7,
        8
      ],
      "get_cost": 2.138938812,
      "put_cost": 0.17496725399999996,
      "storage_cost": 0.026186624657534248,
      "vm_cost": 0.414882,
      "total_cost": 2.754974690657534,
      "get_latency": 551.0,
      "put_latency": 826.5,
      "iq1": [
        5,
        7,
        8
      ],
      "iq2": [
        5,
        7,
        8
      ],
      "iq3": [
        5,
        7,
        8
      ],
      "iq4": [
        5,
        7,
        8
      ]
    },
    {
      "id": 82,
      "protocol": "replication",
      "m": 5,
      "k": 1,
      "selected_dcs": [
        0,
        1,
        5,
        7,
        8
      ],
      "get_cost": 2.1653448120000003,
      "put_cost": 0.17712725399999998,
      "storage_cost": 0.02650991232876712,
      "vm_cost": 0.414882,
      "total_cost": 2.7838639783287675,
      "get_latency": 551.0,
      "put_latency": 826.5,
      "iq1": [
        5,
        7,
        8
      ],
      "iq2": [
        5,
        7,
        8
      ],
      "iq3": [
        5,
        7,
        8
      ],
      "iq4": [
        5,
        7,
        8
      ]
    },
    {
      "id": 83,
      "protocol": "replication",
      "m": 5,
      "k": 1,
      "selected_dcs": [
        0,
        1,
        5,
        7,
        8
      ],
      "get_cost": 2.1917508120000004,
      "put_cost": 0.17928725399999992,
      "storage_cost": 0.026833199999999998,
      "vm_cost": 0.414882,
      "total_cost": 2.8127532660000005,
      "get_latency": 551.0,
      "put_latency": 826.5,
      "iq1": [
        5,
        7,
        8
      ],
      "iq2": [
        5,
        7,
        8
      ],
      "iq3": [
        5,
        7,
        8
      ],
      "iq4": [
        5,
        7,
        8
      ]
    },
    {
      "id": 84,
      "protocol": "replication",
      "m": 5,
      "k": 1,
      "selected_dcs": [
        0,
        1,
        5,
        7,
        8
      ],
      "get_cost": 2.2181568119999997,
      "put_cost": 0.181447254,
      "storage_cost": 0.027156487671232875,
      "vm_cost": 0.414882,
      "total_cost": 2.8416425536712326,
      "get_latency": 551.0,
      "put_latency": 826.5,
      "iq1": [
        5,
        7,
        8
      ],
      "iq2": [
        5,
        7,
        8
      ],
      "iq3": [
        5,
        7,
        8
      ],
      "iq4": [
        5,
        7,
        8
      ]
    },
    {
      "id": 85,
      "protocol": "replication",
      "m": 5,
      "k": 1,
      "selected_dcs": [
        0,
        1,
        5,
        7,
        8
      ],
      "get_cost": 2.244562812,
      "put_cost": 0.18360725399999997,
      "storage_cost": 0.02747977534246575,
      "vm_cost": 0.414882,
      "total_cost": 2.8705318413424656,
      "get_latency": 551.0,
      "put_latency": 826.5,
      "iq1": [
        5,
        7,
        8
      ],
      "iq2": [
        5,
        7,
        8
      ],
      "iq3": [
        5,
        7,
        8
      ],
      "iq4": [
        5,
        7,
        8
      ]
    },
    {
      "id": 86,
      "protocol": "replication",
      "m": 5,
      "k": 1,
      "selected_dcs": [
        0,
        1,
        5,
        7,
        8
      ],
      "get_cost": 2.270968812,
      "put_cost": 0.185767254,
      "storage_cost": 0.027803063013698632,
      "vm_cost": 0.414882,
      "total_cost": 2.8994211290136986,
      "get_latency": 551.0,
      "put_latency": 826.5,
      "iq1": [
        5,
        7,
        8
      ],
      "iq2": [
        5,
        7,
        8
      ],
      "iq3": [
        5,
        7,
        8
      ],
      "iq4": [
        5,
        7,
        8
      ]
    },
    {
      "id": 87,
      "protocol": "replication",
      "m": 5,
      "k": 1,
      "selected_dcs": [
        0,
        1,
        5,
        7,
        8
      ],
      "get_cost": 2.297374812,
      "put_cost": 0.187927254,
      "storage_cost": 0.028126350684931502,
      "vm_cost": 0.414882,
      "total_cost": 2.9283104166849316,
      "get_latency": 551.0,
      "put_latency": 826.5,
      "iq1": [
        5,
        7,
        8
      ],
      "iq2": [
        5,
        7,
        8
      ],
      "iq3": [
        5,
        7,
        8
      ],
      "iq4": [
        5,
        7,
        8
      ]
    },
    {
      "id": 88,
      "protocol": "replication",
      "m": 5,
      "k": 1,
      "selected_dcs": [
        0,
        1,
        5,
        7,
        8
      ],
      "get_cost": 2.323780812,
      "put_cost": 0.19008725399999996,
      "storage_cost": 0.02844963835616438,
      "vm_cost": 0.414882,
      "total_cost": 2.957199704356164,
      "get_latency": 551.0,
      "put_latency": 826.5,
      "iq1": [
        5,
        7,
        8
      ],
      "iq2": [
        5,
        7,
        8
      ],
      "iq3": [
        5,
        7,
        8
      ],
      "iq4": [
        5,
        7,
        8
      ]
    },
    {
      "id": 89,
      "protocol": "replication",
      "m": 5,
      "k": 1,
      "selected_dcs": [
        0,
        1,
        5,
        7,
        8
      ],
      "get_cost": 2.350186812,
      "put_cost": 0.19224725399999995,
      "storage_cost": 0.028772926027397255,
      "vm_cost": 0.414882,
      "total_cost": 2.986088992027397,
      "get_latency": 551.0,
      "put_latency": 826.5,
      "iq1": [
        5,
        7,
        8
      ],
      "iq2": [
        5,
        7,
        8
      ],
      "iq3": [
        5,
        7,
        8
      ],
      "iq4": [
        5,
        7,
        8
      ]
    },
    {
      "id": 90,
      "protocol": "replication",
      "m": 5,
      "k": 1,
      "selected_dcs": [
        0,
        1,
        5,
        7,
        8
      ],
      "get_cost": 2.3765928119999997,
      "put_cost": 0.19440725399999992,
      "storage_cost": 0.029096213698630132,
      "vm_cost": 0.414882,
      "total_cost": 3.0149782796986297,
      "get_latency": 551.0,
      "put_latency": 826.5,
      "iq1": [
        5,
        7,
        8
      ],
      "iq2": [
        5,
        7,
        8
      ],
      "iq3": [
        5,
        7,
        8
      ],
      "iq4": [
        5,
        7,
        8
      ]
    },
    {
      "id": 91,
      "protocol": "replication",
      "m": 5,
      "k": 1,
      "selected_dcs": [
        0,
        1,
        5,
        7,
        8
      ],
      "get_cost": 2.4029988120000003,
      "put_cost": 0.196567254,
      "storage_cost": 0.029419501369863016,
      "vm_cost": 0.414882,
      "total_cost": 3.043867567369863,
      "get_latency": 551.0,
      "put_latency": 826.5,
      "iq1": [
        5,
        7,
        8
      ],
      "iq2": [
        5,
        7,
        8
      ],
      "iq3": [
        5,
        7,
        8
      ],
      "iq4": [
        5,
        7,
        8
      ]
    },
    {
      "id": 92,
      "protocol": "replication",
      "m": 5,
      "k": 1,
      "selected_dcs": [
        0,
        1,
        5,
        7,
        8
      ],
      "get_cost": 2.429404812,
      "put_cost": 0.19872725399999994,
      "storage_cost": 0.029742789041095893,
      "vm_cost": 0.414882,
      "total_cost": 3.0727568550410957,
      "get_latency": 551.0,
      "put_latency": 826.5,
      "iq1": [
        5,
        7,
        8
      ],
      "iq2": [
        5,
        7,
        8
      ],
      "iq3": [
        5,
        7,
        8
      ],
      "iq4": [
        5,
        7,
        8
      ]
    },
    {
      "id": 93,
      "protocol": "replication",
      "m": 5,
      "k": 1,
      "selected_dcs": [
        0,
        1,
        5,
        7,
        8
      ],
      "get_cost": 2.4558108119999997,
      "put_cost": 0.200887254,
      "storage_cost": 0.03006607671232877,
      "vm_cost": 0.414882,
      "total_cost": 3.1016461427123283,
      "get_latency": 551.0,
      "put_latency": 826.5,
      "iq1": [
        5,
        7,
        8
      ],
      "iq2": [
        5,
        7,
        8
      ],
      "iq3": [
        5,
        7,
        8
      ],
      "iq4": [
        5,
        7,
        8
      ]
    },
    {
      "id": 94,
      "protocol": "replication",
      "m": 5,
      "k": 1,
      "selected_dcs": [
        0,
        1,
        5,
        7,
        8
      ],
      "get_cost": 2.4822168119999994,
      "put_cost": 0.20304725399999993,
      "storage_cost": 0.03038936438356164,
      "vm_cost": 0.414882,
      "total_cost": 3.130535430383561,
      "get_latency": 551.0,
      "put_latency": 826.5,
      "iq1": [
        5,
        7,
        8
      ],
      "iq2": [
        5,
        7,
        8
      ],
      "iq3": [
        5,
        7,
        8
      ],
      "iq4": [
        5,
        7,
        8
      ]
    },
    {
      "id": 95,
      "protocol": "replication",
      "m": 5,
      "k": 1,
      "selected_dcs": [
        0,
        1,
        5,
        7,
        8
      ],
      "get_cost": 2.508622811999999,
      "put_cost": 0.20520725399999995,
      "storage_cost": 0.030712652054794516,
      "vm_cost": 0.414882,
      "total_cost": 3.1594247180547934,
      "get_latency": 551.0,
      "put_latency": 826.5,
      "iq1": [
        5,
        7,
        8
      ],
      "iq2": [
        5,
        7,
        8
      ],
      "iq3": [
        5,
        7,
        8
      ],
      "iq4": [
        5,
        7,
        8
      ]
    },
    {
      "id": 96,
      "protocol": "replication",
      "m": 5,
      "k": 1,
      "selected_dcs": [
        0,
        1,
        5,
        7,
        8
      ],
      "get_cost": 2.535028812,
      "put_cost": 0.20736725399999995,
      "storage_cost": 0.031035939726027396,
      "vm_cost": 0.414882,
      "total_cost": 3.1883140057260273,
      "get_latency": 551.0,
      "put_latency": 826.5,
      "iq1": [
        5,
        7,
        8
      ],
      "iq2": [
        5,
        7,
        8
      ],
      "iq3": [
        5,
        7,
        8
      ],
      "iq4": [
        5,
        7,
        8
      ]
    },
    {
      "id": 97,
      "protocol": "replication",
      "m": 5,
      "k": 1,
      "selected_dcs": [
        0,
        1,
        5,
        7,
        8
      ],
      "get_cost": 2.561434812,
      "put_cost": 0.209527254,
      "storage_cost": 0.03135922739726028,
      "vm_cost": 0.414882,
      "total_cost": 3.2172032933972603,
      "get_latency": 551.0,
      "put_latency": 826.5,
      "iq1": [
        5,
        7,
        8
      ],
      "iq2": [
        5,
        7,
        8
      ],
      "iq3": [
        5,
        7,
        8
      ],
      "iq4": [
        5,
        7,
        8
      ]
    },
    {
      "id": 98,
      "protocol": "replication",
      "m": 5,
      "k": 1,
      "selected_dcs": [
        0,
        1,
        5,
        7,
        8
      ],
      "get_cost": 2.5878408119999996,
      "put_cost": 0.2116872539999999,
      "storage_cost": 0.03168251506849315,
      "vm_cost": 0.414882,
      "total_cost": 3.246092581068493,
      "get_latency": 551.0,
      "put_latency": 826.5,
      "iq1": [
        5,
        7,
        8
      ],
      "iq2": [
        5,
        7,
        8
      ],
      "iq3": [
        5,
        7,
        8
      ],
      "iq4": [
        5,
        7,
        8
      ]
    },
    {
      "id": 99,
      "protocol": "replication",
      "m": 5,
      "k": 1,
      "selected_dcs": [
        0,
        1,
        5,
        7,
        8
      ],
      "get_cost": 2.614246812,
      "put_cost": 0.21384725399999996,
      "storage_cost": 0.03200580273972602,
      "vm_cost": 0.414882,
      "total_cost": 3.2749818687397263,
      "get_latency": 551.0,
      "put_latency": 826.5,
      "iq1": [
        5,
        7,
        8
      ],
      "iq2": [
        5,
        7,
        8
      ],
      "iq3": [
        5,
        7,
        8
      ],
      "iq4": [
        5,
        7,
        8
      ]
    }
  ],
  "overall_cost": 184.48593088605472,
  "get_cost": 130.72470136200005,
  "put_cost": 10.692723671999994,
  "storage_cost": 1.6001418520547943,
  "vm_cost": 41.46836399999993,
  "time_period_hrs": 100.0
}